{
    "created_time": "2018-09-08T06:35:26Z",
    "files": [
        {
            "attachment_folder": "",
            "attachments": [
            ],
            "created_time": "2018-09-08T06:35:28Z",
            "modified_time": "2018-09-08T06:35:28Z",
            "name": "[POI2008]POC-Trains.md"
        },
        {
            "attachment_folder": "",
            "attachments": [
            ],
            "created_time": "2019-01-13T12:26:16Z",
            "modified_time": "2019-01-13T12:26:16Z",
            "name": "[BJWC2018]八维.md"
        }
    ],
    "sub_directories": [
    ],
    "version": "1"
}
